{
  "name": "Leila Sanders",
  "age": 24,
  "address": {
    "street": "Ziwu Road",
    "city": "Cohpiwil",
    "state": "KS",
    "zip": "21860"
  },
  "contact": {
    "phone": "(959) 506-7168",
    "servicePhone": "800376719"
  },
  "birthday": "2001-07-23T00:32:29.016Z",
  "ip": "181.156.108.220",
  "foo": "bar",
  "profile": {
    "about": "Dueni hifa gupruwhal aj ivo ukzaho ri ma moz rovduzih ko ru. Si gagahkol lu ha bo tav devzi zu jevaud jet defuke koz giatsop upofoze feguca akoriv efunuv hegcuda. Jafwawom him opewo cew pegipas aterizi dusulma mefhavba ti cu ejigojsa ok teih ecaedjaj deta arike lemonec on. Tewavga dojeklu weez enimacani diani nuimumak pic teebeje umiw ol onidezmed saic hoc fettumugo jinunog woshaj. Igpepac kohoj cemsawraj neavuifa ruvimu unovepu ziktef kuhege agu pellatec nouk dumup tor oczevur.",
    "bio": "Ruwaz minoda sohvi ej weug nichagzun edovugom tebof hosilo zez ironauja ewjotfac ne jok cipohked iwlocan lewserez. Romodjuv duwvifu siruhiga uzegel pispico mesur zorhilo ajgulkub cizaviri jik vafis gukaro bup. Jolus jikubow nacde meje bod bov husak gudac bo ges lagholti upote hozifko nuvujo zi gal. Omfefa verduti pu husijet bu uhevasve din siejuwe rozihco hilimgo gotemadiz ilekebvu agirizfit noreko fessahda fig."
  },
  "apiKey": "a17ebedd7713b1f6477de99495cc1722132e8b5068a695d641834ac2e8847169",
  "currency": {
    "code": "CUC",
    "name": "Cuba Convertible Peso"
  }
}