{
  "name": "Elva Fisher",
  "age": 27,
  "address": {
    "street": "Wofav Loop",
    "city": "Vapsava",
    "state": "DE",
    "zip": "63856"
  },
  "contact": {
    "phone": "(918) 639-1132",
    "servicePhone": "800773294"
  },
  "birthday": "1973-03-06T19:36:44.490Z",
  "ip": "94.205.238.196",
  "foo": "bar",
  "profile": {
    "about": "Powev dudivwe bonof bu ejtilvo ku he op picvuota addaf cafas irfuntut ju abvaf naga je. Iferolehe ala kepku dokda tikitda tapotfo sugeke itli av sareses manibup wofrezumo. Urero wig taebitol heopiha heko pef ca urma juw kajuwhi nah ife holal. Sedmowhal sugij botno umkiv noliile nur cu jutmiz lohbunu wepza ton linrar fohiuj ri enhis suwte abji moutoco. Gu hit go jut ifijetfik hebevaz su enli eg jog pala udu tegu detivi.",
    "bio": "Ohufe adhonob ica ujbu lubulsev ujla urofuofe vis ebu hucez deghac jodu cececfik etavude vigkez dowbi zizpu. Vah puhaufi rurrac gohet susem egiwic dac awda kim illikli fahirib sewfivpe ki hih direlbe sasizbi rop. Pukuw lifpaige gebvurik venowfaf wo duwjecav jevwo ivudeh ta sos nusepug tuetdi bo oci urdizaku."
  },
  "apiKey": "54f16de8fb22682c1ea82e0d993b807ce18e4e667a689c1a0106ce564f128fdd",
  "currency": {
    "code": "KWD",
    "name": "Kuwait Dinar"
  }
}