{
  "name": "Lida Matthews",
  "age": 47,
  "address": {
    "street": "Novoj Turnpike",
    "city": "Egisiduh",
    "state": "OH",
    "zip": "21588"
  },
  "contact": {
    "phone": "(558) 827-7962",
    "servicePhone": "800679174"
  },
  "birthday": "1973-10-22T14:00:06.961Z",
  "ip": "35.55.39.90",
  "foo": "bar",
  "profile": {
    "about": "Mekni otzik izioci gif builegot ha ohafugan suuveleh guji ucpome hesece ruf lujo evanubzer mebidu dafapica jev. Dez ruavwok ke ciku ze dova ji esase ugahujdu gaj winda bub dedci konwivce dihagji cuas wizreda. Ru oc nempadba wud ruje veza kot lirdimir tu cinwelam ro seordor vobubjol pa pejojar ak.",
    "bio": "Noas doto ref cutipi ma jerzuzho fepfekaho abta muhocneb ga pifevelam ec. Fujib red laudsoj negjakwub bulfo wa feco up bivituti bi rop fihorubo ez zelav doniro de. Fol hif honabsu badco gog bokgob hem jajip ce babilej gajudvet uze. Lahmaafo wauza zactegij loscup nen jir niborsos uridjub if wo sa fivopav jurreeno ibdovo rul newfa hovbi gaf."
  },
  "apiKey": "a04126a653ed23a8342061250cf308ba81eeafc9077d362373b817df9eeb034e",
  "currency": {
    "code": "KRW",
    "name": "Korea (South) Won"
  }
}