{
  "name": "Clayton Holloway",
  "age": 34,
  "address": {
    "street": "Cobza River",
    "city": "Tiberu",
    "state": "MO",
    "zip": "15253"
  },
  "contact": {
    "phone": "(508) 578-3399",
    "servicePhone": "800186439"
  },
  "birthday": "1970-09-10T06:11:55.185Z",
  "ip": "33.50.193.26",
  "foo": "bar",
  "profile": {
    "about": "Il nogceggag sohcuvjaf tuf coltiera la vefid ibe mowlupbid iw iw dicgegcic gugebpiz wuafe keknimo dan hezibevup. Itta fetor kowbobuc ika derdeov kohijdi miz mi cu deato gek zimwi diah ohma. Bad woaki ji edi moikwa ziwazdi radawor fususe idakuvip hub imalu lu tidjadlab wikluc az le ropha eluovated. Tom no ci bub tiujo mu lujag de idibafke mo idcieti fukfeihu ugevuh uz bufwejpe saetu ti. Hewno lo ma pu masu desiriz jodime joli ulke fuehu nirwo nerimmo dav.",
    "bio": "Soag cekrob woatdud nuffodmet lawubian arore cumpadvaz lo azrapi noiwu fafanzu huin najub meuza. Tikjinu sowsuli piakekuv ti cep kofu lem dac hofbul tadeud jupozcak un wu se uzi izipelo za powasal. Rohpamjeh hu tezgo kiscabnud bu advoge wocopafo coajhuj urge dup sirahe norwaes owove taf jovaf. Rizdur nu tizha ed rinhetfim winaw nihvi konwa fugcaos likifukam lij jeskeog ijeih pafla wodoki fugo. Vezuife ubafu az noslewa en vod gowubuw sokke urdal tu gututitac kuw gak ci rir domuda zi rid."
  },
  "apiKey": "c54868712a6226d6181297d533d52ad0f4aad0a6c202e2c1a2d12b7848607066",
  "currency": {
    "code": "MAD",
    "name": "Morocco Dirham"
  }
}